mlengineerbelvo/__init__.py
mlengineerbelvo/config/config.py
mlengineerbelvo/config/pipeline.json
mlengineerbelvo/execution.py
mlengineerbelvo/utils/constants.py
mlengineerbelvo/utils/utils.py
mlengineerbelvo-0.1.0.dist-info/LICENSE
mlengineerbelvo-0.1.0.dist-info/WHEEL
mlengineerbelvo-0.1.0.dist-info/METADATA
mlengineerbelvo-0.1.0.dist-info/RECORD
