Metadata-Version: 2.1
Name: mlengineerbelvo
Version: 0.1.0
Summary: ML engineer Test Case - Belvo
License: MIT
Author: Miguel Arquez Abdala
Requires-Python: >=3.9,<3.11
Classifier: License :: OSI Approved :: MIT License
Classifier: Programming Language :: Python :: 3
Classifier: Programming Language :: Python :: 3.10
Classifier: Programming Language :: Python :: 3.9
Requires-Dist: boto3 (>=1.24.36,<2.0.0)
Requires-Dist: feast (>=0.22.1,<0.23.0)
Requires-Dist: mlflow (>=1.27.0,<2.0.0)
Requires-Dist: numpy (>=1.23.1,<2.0.0)
Requires-Dist: pandas (>=1.4.3,<2.0.0)
Requires-Dist: python-json-config (>=1.2.3,<2.0.0)
Requires-Dist: scikit-learn (>=1.1.1,<2.0.0)
Requires-Dist: xgboost (>=1.6.1,<2.0.0)
